graphjoiner/__init__.py
graphjoiner/requests.py
graphjoiner/util.py
graphjoiner-0.3.1.dist-info/DESCRIPTION.rst
graphjoiner-0.3.1.dist-info/METADATA
graphjoiner-0.3.1.dist-info/RECORD
graphjoiner-0.3.1.dist-info/WHEEL
graphjoiner-0.3.1.dist-info/metadata.json
graphjoiner-0.3.1.dist-info/top_level.txt
