Metadata-Version: 2.0
Name: graphjoiner
Version: 0.3.1
Summary: Implementing GraphQL with joins
Home-page: http://github.com/healx/python-graphjoiner
Author: Michael Williamson
Author-email: mike@zwobble.org
License: UNKNOWN
Keywords: graphql graph join
Platform: UNKNOWN
Classifier: Development Status :: 4 - Beta
Classifier: Intended Audience :: Developers
Classifier: Programming Language :: Python
Classifier: Programming Language :: Python :: 2
Classifier: Programming Language :: Python :: 2.7
Classifier: Programming Language :: Python :: 3
Classifier: Programming Language :: Python :: 3.3
Classifier: Programming Language :: Python :: 3.4
Classifier: Programming Language :: Python :: 3.5
Requires-Dist: attrs (>=16.1.0,<17)
Requires-Dist: graphql-core (<0.6,>=0.5.3)
